{"cameraMode":{"drawMode":0,"name":"Shaded","section":"Shading Mode"},"sceneLighting":true,"audioPlay":false,"sceneViewState":{"showFog":true,"showMaterialUpdate":false,"showSkybox":true,"showFlares":true,"showImageEffects":true,"showParticleSystems":true,"showVisualEffectGraphs":true,"m_FxEnabled":true},"in2DMode":false,"pivot":{"x":392.3101806640625,"y":451.3331298828125,"z":9.729049682617188},"rotation":{"x":0.22975294291973115,"y":0.0,"z":0.0,"w":0.9732490181922913},"size":99.20002746582031,"orthographic":false}